{
  "YsFGAT3iJS8": {
    "id": "YsFGAT3iJS8",
    "snippet": {
      "publishedAt": "2023-08-26T09:00:17Z",
      "channelId": "UCbwtBGLYpea4eIk-gocqJuw",
      "title": "Graduation Special Message - Shine On!",
      "channelTitle": "Lana Shikami / \u7345\u5b88\u30e9\u30ca [PRISM Project]"
    }
  },
  "_owyi9s_8Ew": {
    "id": "_owyi9s_8Ew",
    "snippet": {
      "publishedAt": "2023-07-23T23:48:14Z",
      "channelId": "UCbwtBGLYpea4eIk-gocqJuw",
      "title": "THEME PARK RIDE SAFETY CHALLENGE \u3010PRISMProject | Lana Shikami\u3011",
      "channelTitle": "Lana Shikami / \u7345\u5b88\u30e9\u30ca [PRISM Project]"
    },
    "contentDetails": {
      "duration": "PT2H41M15S",
      "dimension": "2d",
      "definition": "hd",
      "caption": "false",
      "licensedContent": true,
      "contentRating": {},
      "projection": "rectangular"
    },
    "liveStreamingDetails": {
      "actualStartTime": "2023-07-23T20:58:58Z",
      "actualEndTime": "2023-07-23T23:40:08Z",
      "scheduledStartTime": "2023-07-23T21:00:00Z"
    }
  },
  "6jHVc73bpO4": {
    "id": "6jHVc73bpO4",
    "snippet": {
      "publishedAt": "2023-07-23T09:59:19Z",
      "channelId": "UCbwtBGLYpea4eIk-gocqJuw",
      "title": "WILL THIS END TODAY?!\u3010PRISMProject | Lana Shikami\u3011",
      "channelTitle": "Lana Shikami / \u7345\u5b88\u30e9\u30ca [PRISM Project]"
    },
    "contentDetails": {
      "duration": "PT1H49M41S",
      "dimension": "2d",
      "definition": "hd",
      "caption": "false",
      "licensedContent": true,
      "contentRating": {},
      "projection": "rectangular"
    },
    "liveStreamingDetails": {
      "actualStartTime": "2023-07-22T20:02:51Z",
      "actualEndTime": "2023-07-22T21:52:25Z",
      "scheduledStartTime": "2023-07-22T20:00:00Z"
    }
  },
  "wj9pIWR8LQc": {
    "id": "wj9pIWR8LQc",
    "snippet": {
      "publishedAt": "2023-07-18T23:41:09Z",
      "channelId": "UCbwtBGLYpea4eIk-gocqJuw",
      "title": "It's about time we played this one... \u3010PRISMProject | Lana Shikami\u3011",
      "channelTitle": "Lana Shikami / \u7345\u5b88\u30e9\u30ca [PRISM Project]"
    },
    "contentDetails": {
      "duration": "PT2H28M50S",
      "dimension": "2d",
      "definition": "hd",
      "caption": "false",
      "licensedContent": true,
      "contentRating": {},
      "projection": "rectangular"
    },
    "liveStreamingDetails": {
      "actualStartTime": "2023-07-18T21:03:42Z",
      "actualEndTime": "2023-07-18T23:32:32Z",
      "scheduledStartTime": "2023-07-18T21:00:00Z"
    }
  },
  "3iUPEpnN9Xg": {
    "id": "3iUPEpnN9Xg",
    "snippet": {
      "publishedAt": "2023-07-18T01:19:55Z",
      "channelId": "UCbwtBGLYpea4eIk-gocqJuw",
      "title": "GIRLBOSSES TAKE OVER A THEME PARK w/@RitaKamishiro \u3010PRISMProject | Lana Shikami\u3011",
      "channelTitle": "Lana Shikami / \u7345\u5b88\u30e9\u30ca [PRISM Project]"
    },
    "contentDetails": {
      "duration": "PT2H53M26S",
      "dimension": "2d",
      "definition": "hd",
      "caption": "false",
      "licensedContent": false,
      "contentRating": {},
      "projection": "rectangular"
    },
    "liveStreamingDetails": {
      "actualStartTime": "2023-07-17T22:00:30Z",
      "actualEndTime": "2023-07-18T00:53:54Z",
      "scheduledStartTime": "2023-07-17T22:00:00Z"
    }
  },
  "-wgKarwgyFk": {
    "id": "-wgKarwgyFk",
    "snippet": {
      "publishedAt": "2023-07-17T11:18:50Z",
      "channelId": "UCbwtBGLYpea4eIk-gocqJuw",
      "title": "Goose-nanigans!\u3010PRISMProject | Lana Shikami\u3011",
      "channelTitle": "Lana Shikami / \u7345\u5b88\u30e9\u30ca [PRISM Project]"
    },
    "contentDetails": {
      "duration": "PT1H55M5S",
      "dimension": "2d",
      "definition": "hd",
      "caption": "false",
      "licensedContent": true,
      "contentRating": {},
      "projection": "rectangular"
    },
    "liveStreamingDetails": {
      "actualStartTime": "2023-07-16T21:17:18Z",
      "actualEndTime": "2023-07-16T23:12:16Z",
      "scheduledStartTime": "2023-07-16T21:15:00Z"
    }
  },
  "GL7R537-knk": {
    "id": "GL7R537-knk",
    "snippet": {
      "publishedAt": "2023-07-15T23:30:24Z",
      "channelId": "UCbwtBGLYpea4eIk-gocqJuw",
      "title": "MARIO TIME, AGAIN?!\u3010PRISMProject | Lana Shikami\u3011",
      "channelTitle": "Lana Shikami / \u7345\u5b88\u30e9\u30ca [PRISM Project]"
    },
    "contentDetails": {
      "duration": "PT2H18M56S",
      "dimension": "2d",
      "definition": "hd",
      "caption": "false",
      "licensedContent": true,
      "contentRating": {},
      "projection": "rectangular"
    },
    "liveStreamingDetails": {
      "actualStartTime": "2023-07-15T21:03:31Z",
      "actualEndTime": "2023-07-15T23:22:25Z",
      "scheduledStartTime": "2023-07-15T21:00:00Z"
    }
  },
  "VDvLI95RXCA": {
    "id": "VDvLI95RXCA",
    "snippet": {
      "publishedAt": "2023-07-14T11:38:36Z",
      "channelId": "UCbwtBGLYpea4eIk-gocqJuw",
      "title": "IT'S MARIO TIME!\u3010PRISMProject | Lana Shikami\u3011",
      "channelTitle": "Lana Shikami / \u7345\u5b88\u30e9\u30ca [PRISM Project]"
    },
    "contentDetails": {
      "duration": "PT3H2M35S",
      "dimension": "2d",
      "definition": "hd",
      "caption": "false",
      "licensedContent": true,
      "contentRating": {},
      "projection": "rectangular"
    },
    "liveStreamingDetails": {
      "actualStartTime": "2023-07-14T08:03:18Z",
      "actualEndTime": "2023-07-14T11:05:48Z",
      "scheduledStartTime": "2023-07-14T08:00:00Z"
    }
  },
  "9wQu0fz6D6c": {
    "id": "9wQu0fz6D6c",
    "snippet": {
      "publishedAt": "2023-07-11T23:41:37Z",
      "channelId": "UCbwtBGLYpea4eIk-gocqJuw",
      "title": "\u3010Spyro: Reignited\u3011100% RUN: WINTER TUNDRA EDITION\u3010PRISMProject | Lana Shikami\u3011",
      "channelTitle": "Lana Shikami / \u7345\u5b88\u30e9\u30ca [PRISM Project]"
    },
    "contentDetails": {
      "duration": "PT2H24M48S",
      "dimension": "2d",
      "definition": "hd",
      "caption": "false",
      "licensedContent": true,
      "contentRating": {},
      "projection": "rectangular"
    },
    "liveStreamingDetails": {
      "actualStartTime": "2023-07-11T20:49:27Z",
      "actualEndTime": "2023-07-11T23:14:11Z",
      "scheduledStartTime": "2023-07-11T21:00:00Z"
    }
  },
  "tURiOL6pH-Y": {
    "id": "tURiOL6pH-Y",
    "snippet": {
      "publishedAt": "2023-07-10T10:29:15Z",
      "channelId": "UCbwtBGLYpea4eIk-gocqJuw",
      "title": "BREAD GAME HARD?! (this is my first time will I have regrets?)\u3010PRISMProject | Lana Shikami\u3011",
      "channelTitle": "Lana Shikami / \u7345\u5b88\u30e9\u30ca [PRISM Project]"
    },
    "contentDetails": {
      "duration": "PT1H16M35S",
      "dimension": "2d",
      "definition": "hd",
      "caption": "false",
      "licensedContent": true,
      "contentRating": {},
      "projection": "rectangular"
    },
    "liveStreamingDetails": {
      "actualStartTime": "2023-07-09T21:06:59Z",
      "actualEndTime": "2023-07-09T22:23:29Z",
      "scheduledStartTime": "2023-07-09T21:00:00Z"
    }
  },
  "aUgpQD3FPjY": {
    "id": "aUgpQD3FPjY",
    "snippet": {
      "publishedAt": "2023-07-08T23:16:02Z",
      "channelId": "UCbwtBGLYpea4eIk-gocqJuw",
      "title": "Pure Comfy Chaos 3DIO ASMR\u3010PRISMProject | Lana Shikami\u3011",
      "channelTitle": "Lana Shikami / \u7345\u5b88\u30e9\u30ca [PRISM Project]"
    },
    "contentDetails": {
      "duration": "PT2H5M19S",
      "dimension": "2d",
      "definition": "hd",
      "caption": "false",
      "licensedContent": true,
      "contentRating": {},
      "projection": "rectangular"
    },
    "liveStreamingDetails": {
      "actualStartTime": "2023-07-08T21:02:20Z",
      "actualEndTime": "2023-07-08T23:07:33Z",
      "scheduledStartTime": "2023-07-08T21:00:00Z"
    }
  },
  "xfDkLrzeSBE": {
    "id": "xfDkLrzeSBE",
    "snippet": {
      "publishedAt": "2023-07-07T10:22:47Z",
      "channelId": "UCbwtBGLYpea4eIk-gocqJuw",
      "title": "LANA STRIKES BACK! (and finishes this game in one stream)\u3010PRISMProject | Lana Shikami\u3011",
      "channelTitle": "Lana Shikami / \u7345\u5b88\u30e9\u30ca [PRISM Project]"
    },
    "contentDetails": {
      "duration": "PT2H10M18S",
      "dimension": "2d",
      "definition": "hd",
      "caption": "false",
      "licensedContent": true,
      "contentRating": {},
      "projection": "rectangular"
    },
    "liveStreamingDetails": {
      "actualStartTime": "2023-07-07T07:59:30Z",
      "actualEndTime": "2023-07-07T10:12:27Z",
      "scheduledStartTime": "2023-07-07T08:00:00Z"
    }
  },
  "w3056UP6lwA": {
    "id": "w3056UP6lwA",
    "snippet": {
      "publishedAt": "2023-07-02T23:43:15Z",
      "channelId": "UCbwtBGLYpea4eIk-gocqJuw",
      "title": "\u3010Spyro: Reignited\u3011100% OR BUST!\u3010PRISMProject | Lana Shikami\u3011",
      "channelTitle": "Lana Shikami / \u7345\u5b88\u30e9\u30ca [PRISM Project]"
    },
    "contentDetails": {
      "duration": "PT2H35M43S",
      "dimension": "2d",
      "definition": "hd",
      "caption": "false",
      "licensedContent": true,
      "contentRating": {},
      "projection": "rectangular"
    },
    "liveStreamingDetails": {
      "actualStartTime": "2023-07-02T20:57:00Z",
      "actualEndTime": "2023-07-02T23:32:42Z",
      "scheduledStartTime": "2023-07-02T21:00:00Z"
    }
  },
  "gic0iTEFw9s": {
    "id": "gic0iTEFw9s",
    "snippet": {
      "publishedAt": "2023-07-02T22:44:27Z",
      "channelId": "UCbwtBGLYpea4eIk-gocqJuw",
      "title": "Entering my brat tamer era\u3010PRISMProject | Lana Shikami\u3011",
      "channelTitle": "Lana Shikami / \u7345\u5b88\u30e9\u30ca [PRISM Project]"
    },
    "contentDetails": {
      "duration": "PT1H31M1S",
      "dimension": "2d",
      "definition": "hd",
      "caption": "false",
      "licensedContent": true,
      "contentRating": {},
      "projection": "rectangular"
    },
    "liveStreamingDetails": {
      "actualStartTime": "2023-07-02T09:06:14Z",
      "actualEndTime": "2023-07-02T10:37:12Z",
      "scheduledStartTime": "2023-07-02T09:00:00Z"
    }
  },
  "OFJH5_QSFu8": {
    "id": "OFJH5_QSFu8",
    "snippet": {
      "publishedAt": "2023-06-30T22:09:20Z",
      "channelId": "UCbwtBGLYpea4eIk-gocqJuw",
      "title": "Chaotic Sun Mommy ASMR Night!\u3010PRISMProject | Lana Shikami\u3011",
      "channelTitle": "Lana Shikami / \u7345\u5b88\u30e9\u30ca [PRISM Project]"
    },
    "contentDetails": {
      "duration": "PT1H58M30S",
      "dimension": "2d",
      "definition": "hd",
      "caption": "false",
      "licensedContent": true,
      "contentRating": {},
      "projection": "rectangular"
    },
    "liveStreamingDetails": {
      "actualStartTime": "2023-06-30T08:05:06Z",
      "actualEndTime": "2023-06-30T10:03:36Z",
      "scheduledStartTime": "2023-06-30T08:00:00Z"
    }
  },
  "Cnvb7YarRYs": {
    "id": "Cnvb7YarRYs",
    "snippet": {
      "publishedAt": "2023-06-27T23:21:12Z",
      "channelId": "UCbwtBGLYpea4eIk-gocqJuw",
      "title": "\u3010Spyro: Reignited\u3011Gateway to Glimmer!!\u3010PRISMProject | Lana Shikami\u3011",
      "channelTitle": "Lana Shikami / \u7345\u5b88\u30e9\u30ca [PRISM Project]"
    },
    "contentDetails": {
      "duration": "PT2H12M36S",
      "dimension": "2d",
      "definition": "hd",
      "caption": "false",
      "licensedContent": true,
      "contentRating": {},
      "projection": "rectangular"
    },
    "liveStreamingDetails": {
      "actualStartTime": "2023-06-27T21:01:01Z",
      "actualEndTime": "2023-06-27T23:13:38Z",
      "scheduledStartTime": "2023-06-27T21:00:00Z"
    }
  },
  "A7YlM8KM48U": {
    "id": "A7YlM8KM48U",
    "snippet": {
      "publishedAt": "2023-06-25T23:45:16Z",
      "channelId": "UCbwtBGLYpea4eIk-gocqJuw",
      "title": "\u3010DINKUM\u3011NEW UPDATES TO THE GAME?!\u3010PRISMProject | Lana Shikami\u3011",
      "channelTitle": "Lana Shikami / \u7345\u5b88\u30e9\u30ca [PRISM Project]"
    },
    "contentDetails": {
      "duration": "PT2H24M17S",
      "dimension": "2d",
      "definition": "hd",
      "caption": "false",
      "licensedContent": true,
      "contentRating": {},
      "projection": "rectangular"
    },
    "liveStreamingDetails": {
      "actualStartTime": "2023-06-25T21:11:00Z",
      "actualEndTime": "2023-06-25T23:35:16Z",
      "scheduledStartTime": "2023-06-25T21:00:00Z"
    }
  },
  "f3Vvl6YR-vs": {
    "id": "f3Vvl6YR-vs",
    "snippet": {
      "publishedAt": "2023-06-24T23:51:28Z",
      "channelId": "UCbwtBGLYpea4eIk-gocqJuw",
      "title": "Intense ASMR Tingle Time w/@AngelStepsASMR \u3010PRISMProject | Lana Shikami\u3011",
      "channelTitle": "Lana Shikami / \u7345\u5b88\u30e9\u30ca [PRISM Project]"
    },
    "contentDetails": {
      "duration": "PT2H29M13S",
      "dimension": "2d",
      "definition": "hd",
      "caption": "false",
      "licensedContent": false,
      "contentRating": {},
      "projection": "rectangular"
    },
    "liveStreamingDetails": {
      "actualStartTime": "2023-06-24T21:13:38Z",
      "actualEndTime": "2023-06-24T23:42:51Z",
      "scheduledStartTime": "2023-06-24T21:15:00Z"
    }
  },
  "7hAxujjn1LE": {
    "id": "7hAxujjn1LE",
    "snippet": {
      "publishedAt": "2023-06-20T23:51:46Z",
      "channelId": "UCbwtBGLYpea4eIk-gocqJuw",
      "title": "It's Joja Time! (with mods)\u3010PRISMProject | Lana Shikami\u3011(Part 2 Stardew Valley Speedrun)",
      "channelTitle": "Lana Shikami / \u7345\u5b88\u30e9\u30ca [PRISM Project]"
    },
    "contentDetails": {
      "duration": "PT2H34M51S",
      "dimension": "2d",
      "definition": "hd",
      "caption": "false",
      "licensedContent": true,
      "contentRating": {},
      "projection": "rectangular"
    },
    "liveStreamingDetails": {
      "actualStartTime": "2023-06-20T21:03:13Z",
      "actualEndTime": "2023-06-20T23:38:04Z",
      "scheduledStartTime": "2023-06-20T21:00:00Z"
    }
  },
  "AhNW-gU0pTk": {
    "id": "AhNW-gU0pTk",
    "snippet": {
      "publishedAt": "2023-06-19T20:51:51Z",
      "channelId": "UCbwtBGLYpea4eIk-gocqJuw",
      "title": "Finding Your Lost Love on a Train [ASMR RP] [F4A] [Strangers to Lovers]",
      "channelTitle": "Lana Shikami / \u7345\u5b88\u30e9\u30ca [PRISM Project]"
    },
    "contentDetails": {
      "duration": "PT15M58S",
      "dimension": "2d",
      "definition": "hd",
      "caption": "false",
      "licensedContent": true,
      "contentRating": {},
      "projection": "rectangular"
    }
  },
  "bykt-g2oC0k": {
    "id": "bykt-g2oC0k",
    "snippet": {
      "publishedAt": "2023-06-19T06:53:41Z",
      "channelId": "UCbwtBGLYpea4eIk-gocqJuw",
      "title": "what is hypnosis?",
      "channelTitle": "Lana Shikami / \u7345\u5b88\u30e9\u30ca [PRISM Project]"
    },
    "contentDetails": {
      "duration": "PT57S",
      "dimension": "2d",
      "definition": "hd",
      "caption": "false",
      "licensedContent": true,
      "contentRating": {},
      "projection": "rectangular"
    }
  },
  "hOT0fbBIpYg": {
    "id": "hOT0fbBIpYg",
    "snippet": {
      "publishedAt": "2023-06-18T23:37:59Z",
      "channelId": "UCbwtBGLYpea4eIk-gocqJuw",
      "title": "\u3010Spyro the Dragon\u3011The Adventure Begins! (part 2)\u3010PRISMProject | Lana Shikami\u3011",
      "channelTitle": "Lana Shikami / \u7345\u5b88\u30e9\u30ca [PRISM Project]"
    },
    "contentDetails": {
      "duration": "PT2H29M24S",
      "dimension": "2d",
      "definition": "hd",
      "caption": "false",
      "licensedContent": true,
      "contentRating": {},
      "projection": "rectangular"
    },
    "liveStreamingDetails": {
      "actualStartTime": "2023-06-18T21:00:06Z",
      "actualEndTime": "2023-06-18T23:29:34Z",
      "scheduledStartTime": "2023-06-18T21:00:00Z"
    }
  },
  "bZnsG1Tjtp8": {
    "id": "bZnsG1Tjtp8",
    "snippet": {
      "publishedAt": "2023-06-16T11:04:06Z",
      "channelId": "UCbwtBGLYpea4eIk-gocqJuw",
      "title": "Can You Speedrun Stardew Valley? (with mods)\u3010PRISMProject | Lana Shikami\u3011",
      "channelTitle": "Lana Shikami / \u7345\u5b88\u30e9\u30ca [PRISM Project]"
    },
    "contentDetails": {
      "duration": "PT2H30M16S",
      "dimension": "2d",
      "definition": "hd",
      "caption": "false",
      "licensedContent": true,
      "contentRating": {},
      "projection": "rectangular"
    },
    "liveStreamingDetails": {
      "actualStartTime": "2023-06-16T08:02:19Z",
      "actualEndTime": "2023-06-16T10:32:36Z",
      "scheduledStartTime": "2023-06-16T08:00:00Z"
    }
  },
  "S9eD4fpK6h4": {
    "id": "S9eD4fpK6h4",
    "snippet": {
      "publishedAt": "2023-06-12T10:52:57Z",
      "channelId": "UCbwtBGLYpea4eIk-gocqJuw",
      "title": "\u3010Spyro: Reignited\u3011The Adventure Begins!\u3010PRISMProject | Lana Shikami\u3011",
      "channelTitle": "Lana Shikami / \u7345\u5b88\u30e9\u30ca [PRISM Project]"
    },
    "contentDetails": {
      "duration": "PT1H44M57S",
      "dimension": "2d",
      "definition": "hd",
      "caption": "false",
      "licensedContent": true,
      "contentRating": {},
      "projection": "rectangular"
    },
    "liveStreamingDetails": {
      "actualStartTime": "2023-06-11T20:57:46Z",
      "actualEndTime": "2023-06-11T22:42:42Z",
      "scheduledStartTime": "2023-06-11T21:00:00Z"
    }
  },
  "jgJ9Lb5GAyg": {
    "id": "jgJ9Lb5GAyg",
    "snippet": {
      "publishedAt": "2023-06-10T23:28:16Z",
      "channelId": "UCbwtBGLYpea4eIk-gocqJuw",
      "title": "Double Chaotic ASMR Mommy Hour w/@huntressspectre\u3010PRISMProject | Lana Shikami\u3011",
      "channelTitle": "Lana Shikami / \u7345\u5b88\u30e9\u30ca [PRISM Project]"
    },
    "contentDetails": {
      "duration": "PT2H5M10S",
      "dimension": "2d",
      "definition": "hd",
      "caption": "false",
      "licensedContent": true,
      "contentRating": {},
      "projection": "rectangular"
    },
    "liveStreamingDetails": {
      "actualStartTime": "2023-06-10T21:05:34Z",
      "actualEndTime": "2023-06-10T23:10:47Z",
      "scheduledStartTime": "2023-06-10T21:00:00Z"
    }
  },
  "ZRQ4eLsu_yQ": {
    "id": "ZRQ4eLsu_yQ",
    "snippet": {
      "publishedAt": "2023-06-08T23:15:34Z",
      "channelId": "UCbwtBGLYpea4eIk-gocqJuw",
      "title": "\u3010DINKUM\u3011WEARY-MU HOURS!\u3010PRISMProject | Lana Shikami\u3011",
      "channelTitle": "Lana Shikami / \u7345\u5b88\u30e9\u30ca [PRISM Project]"
    },
    "contentDetails": {
      "duration": "PT2H8M32S",
      "dimension": "2d",
      "definition": "hd",
      "caption": "false",
      "licensedContent": true,
      "contentRating": {},
      "projection": "rectangular"
    },
    "liveStreamingDetails": {
      "actualStartTime": "2023-06-08T20:59:26Z",
      "actualEndTime": "2023-06-08T23:07:55Z",
      "scheduledStartTime": "2023-06-08T21:00:00Z"
    }
  },
  "xgJ3O6m6zso": {
    "id": "xgJ3O6m6zso",
    "snippet": {
      "publishedAt": "2023-06-06T23:41:52Z",
      "channelId": "UCbwtBGLYpea4eIk-gocqJuw",
      "title": "\u3010CRASH BANDICOOT: WARPED\u3011Can We Finish? (Definitely NOT 100%)\u3010PRISMProject | Lana Shikami\u3011",
      "channelTitle": "Lana Shikami / \u7345\u5b88\u30e9\u30ca [PRISM Project]"
    },
    "contentDetails": {
      "duration": "PT2H27M52S",
      "dimension": "2d",
      "definition": "hd",
      "caption": "false",
      "licensedContent": true,
      "contentRating": {},
      "projection": "rectangular"
    },
    "liveStreamingDetails": {
      "actualStartTime": "2023-06-06T21:04:22Z",
      "actualEndTime": "2023-06-06T23:32:12Z",
      "scheduledStartTime": "2023-06-06T21:00:00Z"
    }
  },
  "BdJNw_43LJ4": {
    "id": "BdJNw_43LJ4",
    "snippet": {
      "publishedAt": "2023-06-04T22:32:59Z",
      "channelId": "UCbwtBGLYpea4eIk-gocqJuw",
      "title": "A Very Serious Hypnosis 101 (with powerpoint)\u3010PRISMProject | Lana Shikami\u3011",
      "channelTitle": "Lana Shikami / \u7345\u5b88\u30e9\u30ca [PRISM Project]"
    },
    "contentDetails": {
      "duration": "PT1H16M31S",
      "dimension": "2d",
      "definition": "hd",
      "caption": "false",
      "licensedContent": true,
      "contentRating": {},
      "projection": "rectangular"
    },
    "liveStreamingDetails": {
      "actualStartTime": "2023-06-04T21:00:28Z",
      "actualEndTime": "2023-06-04T22:16:56Z",
      "scheduledStartTime": "2023-06-04T21:00:00Z"
    }
  },
  "_zxyVfTGoAw": {
    "id": "_zxyVfTGoAw",
    "snippet": {
      "publishedAt": "2023-06-02T11:24:02Z",
      "channelId": "UCbwtBGLYpea4eIk-gocqJuw",
      "title": "\u3010DINKUM\u3011Return of the CROCS!\u3010PRISMProject | Lana Shikami\u3011",
      "channelTitle": "Lana Shikami / \u7345\u5b88\u30e9\u30ca [PRISM Project]"
    },
    "contentDetails": {
      "duration": "PT3H13M39S",
      "dimension": "2d",
      "definition": "hd",
      "caption": "false",
      "licensedContent": true,
      "contentRating": {},
      "projection": "rectangular"
    },
    "liveStreamingDetails": {
      "actualStartTime": "2023-06-02T07:57:24Z",
      "actualEndTime": "2023-06-02T11:11:03Z",
      "scheduledStartTime": "2023-06-02T08:00:00Z"
    }
  },
  "f-SYC76Nukc": {
    "id": "f-SYC76Nukc",
    "snippet": {
      "publishedAt": "2023-05-31T01:23:25Z",
      "channelId": "UCbwtBGLYpea4eIk-gocqJuw",
      "title": "\u3010Banjo-Kazooie\u3011ACTUALLY THE LAST BANJO STREAM!\u3010PRISMProject | Lana Shikami\u3011",
      "channelTitle": "Lana Shikami / \u7345\u5b88\u30e9\u30ca [PRISM Project]"
    },
    "contentDetails": {
      "duration": "PT4H7M8S",
      "dimension": "2d",
      "definition": "hd",
      "caption": "false",
      "licensedContent": true,
      "contentRating": {},
      "projection": "rectangular"
    },
    "liveStreamingDetails": {
      "actualStartTime": "2023-05-30T21:02:45Z",
      "actualEndTime": "2023-05-31T01:09:56Z",
      "scheduledStartTime": "2023-05-30T21:00:00Z"
    }
  },
  "KySQj9hRzFk": {
    "id": "KySQj9hRzFk",
    "snippet": {
      "publishedAt": "2023-05-29T10:32:15Z",
      "channelId": "UCbwtBGLYpea4eIk-gocqJuw",
      "title": "\u3010Karaoke\u3011THE FIRST KARAOKE STREAM\u3010PRISMProject | Lana Shikami\u3011",
      "channelTitle": "Lana Shikami / \u7345\u5b88\u30e9\u30ca [PRISM Project]"
    },
    "contentDetails": {
      "duration": "PT1H21M44S",
      "dimension": "2d",
      "definition": "hd",
      "caption": "false",
      "licensedContent": false,
      "contentRating": {},
      "projection": "rectangular"
    },
    "liveStreamingDetails": {
      "actualStartTime": "2023-05-28T21:02:45Z",
      "actualEndTime": "2023-05-28T22:24:23Z",
      "scheduledStartTime": "2023-05-28T21:00:00Z"
    }
  },
  "OWdDsketTSE": {
    "id": "OWdDsketTSE",
    "snippet": {
      "publishedAt": "2023-05-28T11:19:12Z",
      "channelId": "UCbwtBGLYpea4eIk-gocqJuw",
      "title": "\u3010Just Chatting\u3011EUROVISION 2023 TIERLIST\u3010PRISMProject | Lana Shikami\u3011",
      "channelTitle": "Lana Shikami / \u7345\u5b88\u30e9\u30ca [PRISM Project]"
    },
    "contentDetails": {
      "duration": "PT1H41M6S",
      "dimension": "2d",
      "definition": "hd",
      "caption": "false",
      "licensedContent": true,
      "contentRating": {},
      "projection": "rectangular"
    },
    "liveStreamingDetails": {
      "actualStartTime": "2023-05-27T21:01:43Z",
      "actualEndTime": "2023-05-27T22:42:53Z",
      "scheduledStartTime": "2023-05-27T21:00:00Z"
    }
  },
  "mUoXHYyt4HI": {
    "id": "mUoXHYyt4HI",
    "snippet": {
      "publishedAt": "2023-05-26T11:03:53Z",
      "channelId": "UCbwtBGLYpea4eIk-gocqJuw",
      "title": "\u30103DIO ASMR\u3011Headpats and Ear Rubs with your Sun Goddess!\u3010PRISMProject | Lana Shikami\u3011",
      "channelTitle": "Lana Shikami / \u7345\u5b88\u30e9\u30ca [PRISM Project]"
    },
    "contentDetails": {
      "duration": "PT2H13M43S",
      "dimension": "2d",
      "definition": "hd",
      "caption": "false",
      "licensedContent": true,
      "contentRating": {},
      "projection": "rectangular"
    },
    "liveStreamingDetails": {
      "actualStartTime": "2023-05-26T07:58:33Z",
      "actualEndTime": "2023-05-26T10:12:09Z",
      "scheduledStartTime": "2023-05-26T08:00:00Z"
    }
  },
  "hDdT9bnM7lk": {
    "id": "hDdT9bnM7lk",
    "snippet": {
      "publishedAt": "2023-05-24T00:42:52Z",
      "channelId": "UCbwtBGLYpea4eIk-gocqJuw",
      "title": "\u3010Banjo-Kazooie\u3011This ENDS Today!\u3010PRISMProject | Lana Shikami\u3011",
      "channelTitle": "Lana Shikami / \u7345\u5b88\u30e9\u30ca [PRISM Project]"
    },
    "contentDetails": {
      "duration": "PT3H25M35S",
      "dimension": "2d",
      "definition": "hd",
      "caption": "false",
      "licensedContent": true,
      "contentRating": {},
      "projection": "rectangular"
    },
    "liveStreamingDetails": {
      "actualStartTime": "2023-05-23T20:58:11Z",
      "actualEndTime": "2023-05-24T00:23:52Z",
      "scheduledStartTime": "2023-05-23T21:00:00Z"
    }
  },
  "Sqs06-kIibE": {
    "id": "Sqs06-kIibE",
    "snippet": {
      "publishedAt": "2023-05-22T21:00:10Z",
      "channelId": "UCbwtBGLYpea4eIk-gocqJuw",
      "title": "Lana Shikami Debut Highlights | PRISM Project Gen 5",
      "channelTitle": "Lana Shikami / \u7345\u5b88\u30e9\u30ca [PRISM Project]"
    },
    "contentDetails": {
      "duration": "PT9M34S",
      "dimension": "2d",
      "definition": "hd",
      "caption": "false",
      "licensedContent": true,
      "contentRating": {},
      "projection": "rectangular"
    },
    "liveStreamingDetails": {
      "actualStartTime": "2023-05-22T21:00:10Z",
      "actualEndTime": "2023-05-22T21:11:40Z",
      "scheduledStartTime": "2023-05-22T21:00:00Z"
    }
  },
  "enOCYfIESxI": {
    "id": "enOCYfIESxI",
    "snippet": {
      "publishedAt": "2023-05-21T22:44:10Z",
      "channelId": "UCbwtBGLYpea4eIk-gocqJuw",
      "title": "Monetization + Membership Opening Celebration! \u3010PRISMProject | Lana Shikami\u3011",
      "channelTitle": "Lana Shikami / \u7345\u5b88\u30e9\u30ca [PRISM Project]"
    },
    "contentDetails": {
      "duration": "PT1H33M59S",
      "dimension": "2d",
      "definition": "hd",
      "caption": "false",
      "licensedContent": true,
      "contentRating": {},
      "projection": "rectangular"
    },
    "liveStreamingDetails": {
      "actualStartTime": "2023-05-21T21:03:07Z",
      "actualEndTime": "2023-05-21T22:37:04Z",
      "scheduledStartTime": "2023-05-21T21:00:00Z"
    }
  },
  "wRg4l5bhA4M": {
    "id": "wRg4l5bhA4M",
    "snippet": {
      "publishedAt": "2023-05-21T11:07:55Z",
      "channelId": "UCbwtBGLYpea4eIk-gocqJuw",
      "title": "\u3010Just Chatting\u3011Time to Ponder the Orbs\u3010PRISMProject | Lana Shikami\u3011",
      "channelTitle": "Lana Shikami / \u7345\u5b88\u30e9\u30ca [PRISM Project]"
    },
    "contentDetails": {
      "duration": "PT1H49M56S",
      "dimension": "2d",
      "definition": "hd",
      "caption": "false",
      "licensedContent": true,
      "contentRating": {},
      "projection": "rectangular"
    },
    "liveStreamingDetails": {
      "actualStartTime": "2023-05-20T21:02:50Z",
      "actualEndTime": "2023-05-20T22:52:45Z",
      "scheduledStartTime": "2023-05-20T21:00:00Z"
    }
  },
  "sGCbsBWUC_M": {
    "id": "sGCbsBWUC_M",
    "snippet": {
      "publishedAt": "2023-05-20T22:02:48Z",
      "channelId": "UCbwtBGLYpea4eIk-gocqJuw",
      "title": "\u30103DIO ASMR\u3011Can You Handle the Tingles?\u3010PRISMProject | Lana Shikami\u3011",
      "channelTitle": "Lana Shikami / \u7345\u5b88\u30e9\u30ca [PRISM Project]"
    },
    "contentDetails": {
      "duration": "PT1H52M37S",
      "dimension": "2d",
      "definition": "hd",
      "caption": "false",
      "licensedContent": true,
      "contentRating": {},
      "projection": "rectangular"
    },
    "liveStreamingDetails": {
      "actualStartTime": "2023-05-20T08:02:42Z",
      "actualEndTime": "2023-05-20T09:55:24Z",
      "scheduledStartTime": "2023-05-20T08:00:00Z"
    }
  },
  "fIepCyXsRyI": {
    "id": "fIepCyXsRyI",
    "snippet": {
      "publishedAt": "2023-05-20T19:08:35Z",
      "channelId": "UCbwtBGLYpea4eIk-gocqJuw",
      "title": "how to be the best dommy mommy",
      "channelTitle": "Lana Shikami / \u7345\u5b88\u30e9\u30ca [PRISM Project]"
    },
    "contentDetails": {
      "duration": "PT25S",
      "dimension": "2d",
      "definition": "hd",
      "caption": "false",
      "licensedContent": true,
      "contentRating": {},
      "projection": "rectangular"
    }
  },
  "w7bmIcAgxGM": {
    "id": "w7bmIcAgxGM",
    "snippet": {
      "publishedAt": "2023-05-20T03:46:23Z",
      "channelId": "UCbwtBGLYpea4eIk-gocqJuw",
      "title": "signs my cat LOVES me!",
      "channelTitle": "Lana Shikami / \u7345\u5b88\u30e9\u30ca [PRISM Project]"
    },
    "contentDetails": {
      "duration": "PT21S",
      "dimension": "2d",
      "definition": "hd",
      "caption": "false",
      "licensedContent": true,
      "contentRating": {},
      "projection": "rectangular"
    }
  },
  "64etGTOWlZE": {
    "id": "64etGTOWlZE",
    "snippet": {
      "publishedAt": "2023-05-19T04:26:50Z",
      "channelId": "UCbwtBGLYpea4eIk-gocqJuw",
      "title": "\u3010Human Fall Flat\u3011Can we WEATHER the CHAOS?!\u3010PRISMProject | Lana Shikami\u3011",
      "channelTitle": "Lana Shikami / \u7345\u5b88\u30e9\u30ca [PRISM Project]"
    },
    "contentDetails": {
      "duration": "PT2H13M17S",
      "dimension": "2d",
      "definition": "hd",
      "caption": "false",
      "licensedContent": true,
      "contentRating": {},
      "projection": "rectangular"
    },
    "liveStreamingDetails": {
      "actualStartTime": "2023-05-19T02:03:23Z",
      "actualEndTime": "2023-05-19T04:16:39Z",
      "scheduledStartTime": "2023-05-19T02:00:00Z"
    }
  },
  "vv6jT7s6O04": {
    "id": "vv6jT7s6O04",
    "snippet": {
      "publishedAt": "2023-05-18T07:53:50Z",
      "channelId": "UCbwtBGLYpea4eIk-gocqJuw",
      "title": "sun goddess vtuber blesses your day!",
      "channelTitle": "Lana Shikami / \u7345\u5b88\u30e9\u30ca [PRISM Project]"
    },
    "contentDetails": {
      "duration": "PT30S",
      "dimension": "2d",
      "definition": "hd",
      "caption": "false",
      "licensedContent": true,
      "contentRating": {},
      "projection": "rectangular"
    }
  },
  "mAGKRRCi0PM": {
    "id": "mAGKRRCi0PM",
    "snippet": {
      "publishedAt": "2023-05-17T05:33:19Z",
      "channelId": "UCbwtBGLYpea4eIk-gocqJuw",
      "title": "\u3010CRASH BANDICOOT\u3011Can We Finish? (Probably, not 100%)\u3010PRISMProject | Lana Shikami\u3011",
      "channelTitle": "Lana Shikami / \u7345\u5b88\u30e9\u30ca [PRISM Project]"
    },
    "contentDetails": {
      "duration": "PT3H10M46S",
      "dimension": "2d",
      "definition": "hd",
      "caption": "false",
      "licensedContent": true,
      "contentRating": {},
      "projection": "rectangular"
    },
    "liveStreamingDetails": {
      "actualStartTime": "2023-05-17T01:57:30Z",
      "actualEndTime": "2023-05-17T05:08:12Z",
      "scheduledStartTime": "2023-05-17T02:00:00Z"
    }
  },
  "0hLF-5HEQqM": {
    "id": "0hLF-5HEQqM",
    "snippet": {
      "publishedAt": "2023-05-15T04:50:49Z",
      "channelId": "UCbwtBGLYpea4eIk-gocqJuw",
      "title": "\u3010THE SIMS\u3011Is Sims 4 Worth It?\u3010PRISMProject | Lana Shikami\u3011",
      "channelTitle": "Lana Shikami / \u7345\u5b88\u30e9\u30ca [PRISM Project]"
    },
    "contentDetails": {
      "duration": "PT2H31M50S",
      "dimension": "2d",
      "definition": "hd",
      "caption": "false",
      "licensedContent": true,
      "contentRating": {},
      "projection": "rectangular"
    },
    "liveStreamingDetails": {
      "actualStartTime": "2023-05-15T01:58:46Z",
      "actualEndTime": "2023-05-15T04:30:35Z",
      "scheduledStartTime": "2023-05-15T02:00:00Z"
    }
  },
  "D9vNUFcSOVc": {
    "id": "D9vNUFcSOVc",
    "snippet": {
      "publishedAt": "2023-05-14T04:55:39Z",
      "channelId": "UCbwtBGLYpea4eIk-gocqJuw",
      "title": "\u3010SUN HAVEN\u3011Here Comes The Sun (Haven Collab)\u3010PRISMProject | Lana Shikami\u3011",
      "channelTitle": "Lana Shikami / \u7345\u5b88\u30e9\u30ca [PRISM Project]"
    },
    "contentDetails": {
      "duration": "PT2H24M4S",
      "dimension": "2d",
      "definition": "hd",
      "caption": "false",
      "licensedContent": true,
      "contentRating": {},
      "projection": "rectangular"
    },
    "liveStreamingDetails": {
      "actualStartTime": "2023-05-14T02:01:47Z",
      "actualEndTime": "2023-05-14T04:25:52Z",
      "scheduledStartTime": "2023-05-14T02:00:00Z"
    }
  },
  "Ij0VHKOf838": {
    "id": "Ij0VHKOf838",
    "snippet": {
      "publishedAt": "2023-05-13T00:11:45Z",
      "channelId": "UCbwtBGLYpea4eIk-gocqJuw",
      "title": "\u3010ASMR\u3011LATE NIGHT WITH SUN MOMMY\u3010PRISMProject | Lana Shikami\u3011",
      "channelTitle": "Lana Shikami / \u7345\u5b88\u30e9\u30ca [PRISM Project]"
    },
    "contentDetails": {
      "duration": "PT1H46M24S",
      "dimension": "2d",
      "definition": "hd",
      "caption": "false",
      "licensedContent": true,
      "contentRating": {},
      "projection": "rectangular"
    },
    "liveStreamingDetails": {
      "actualStartTime": "2023-05-12T07:59:10Z",
      "actualEndTime": "2023-05-12T09:45:28Z",
      "scheduledStartTime": "2023-05-12T08:00:00Z"
    }
  },
  "209wCSWzjTU": {
    "id": "209wCSWzjTU",
    "snippet": {
      "publishedAt": "2023-05-10T04:11:39Z",
      "channelId": "UCbwtBGLYpea4eIk-gocqJuw",
      "title": "\u3010Banjo-Kazooie\u3011Birb, Bear and a Heavy Dose of Eurovision Ranting!\u3010PRISMProject | Lana Shikami\u3011",
      "channelTitle": "Lana Shikami / \u7345\u5b88\u30e9\u30ca [PRISM Project]"
    },
    "contentDetails": {
      "duration": "PT2H2M20S",
      "dimension": "2d",
      "definition": "hd",
      "caption": "false",
      "licensedContent": true,
      "contentRating": {},
      "projection": "rectangular"
    },
    "liveStreamingDetails": {
      "actualStartTime": "2023-05-10T01:58:03Z",
      "actualEndTime": "2023-05-10T04:00:29Z",
      "scheduledStartTime": "2023-05-10T02:00:00Z"
    }
  },
  "e8Cfzy9Z8Bg": {
    "id": "e8Cfzy9Z8Bg",
    "snippet": {
      "publishedAt": "2023-05-08T04:56:27Z",
      "channelId": "UCbwtBGLYpea4eIk-gocqJuw",
      "title": "\u3010DINKUM\u3011GOING DEEP (MINING)\u3010PRISMProject | Lana Shikami\u3011",
      "channelTitle": "Lana Shikami / \u7345\u5b88\u30e9\u30ca [PRISM Project]"
    },
    "contentDetails": {
      "duration": "PT2H29M50S",
      "dimension": "2d",
      "definition": "hd",
      "caption": "false",
      "licensedContent": true,
      "contentRating": {},
      "projection": "rectangular"
    },
    "liveStreamingDetails": {
      "actualStartTime": "2023-05-08T01:56:15Z",
      "actualEndTime": "2023-05-08T04:26:04Z",
      "scheduledStartTime": "2023-05-08T02:00:00Z"
    }
  },
  "2rO2hOKze4A": {
    "id": "2rO2hOKze4A",
    "snippet": {
      "publishedAt": "2023-05-07T16:09:06Z",
      "channelId": "UCbwtBGLYpea4eIk-gocqJuw",
      "title": "\u3010Just Chatting\u3011SUNDAY WITH YOUR SUN GODDESS!\u3010PRISMProject | Lana Shikami\u3011",
      "channelTitle": "Lana Shikami / \u7345\u5b88\u30e9\u30ca [PRISM Project]"
    },
    "contentDetails": {
      "duration": "PT1H56M31S",
      "dimension": "2d",
      "definition": "hd",
      "caption": "false",
      "licensedContent": true,
      "contentRating": {},
      "projection": "rectangular"
    },
    "liveStreamingDetails": {
      "actualStartTime": "2023-05-07T01:55:32Z",
      "actualEndTime": "2023-05-07T03:52:04Z",
      "scheduledStartTime": "2023-05-07T02:00:00Z"
    }
  },
  "37P0oPPcUUc": {
    "id": "37P0oPPcUUc",
    "snippet": {
      "publishedAt": "2023-05-07T11:00:07Z",
      "channelId": "UCbwtBGLYpea4eIk-gocqJuw",
      "title": "Mommy Sun Goddess Appears in Your Room [ASMR RP] [F4A] [Soft Spoken]",
      "channelTitle": "Lana Shikami / \u7345\u5b88\u30e9\u30ca [PRISM Project]"
    },
    "contentDetails": {
      "duration": "PT10M28S",
      "dimension": "2d",
      "definition": "hd",
      "caption": "false",
      "licensedContent": true,
      "contentRating": {},
      "projection": "rectangular"
    },
    "liveStreamingDetails": {
      "actualStartTime": "2023-05-07T11:00:07Z",
      "actualEndTime": "2023-05-07T11:12:34Z",
      "scheduledStartTime": "2023-05-07T11:00:00Z"
    }
  },
  "CpDGbLJEQaw": {
    "id": "CpDGbLJEQaw",
    "snippet": {
      "publishedAt": "2023-05-05T03:48:41Z",
      "channelId": "UCbwtBGLYpea4eIk-gocqJuw",
      "title": "\u3010ASMR\u3011Comfortable Chaos Hours!\u3010PRISMProject | Lana Shikami\u3011",
      "channelTitle": "Lana Shikami / \u7345\u5b88\u30e9\u30ca [PRISM Project]"
    },
    "contentDetails": {
      "duration": "PT1H43M17S",
      "dimension": "2d",
      "definition": "hd",
      "caption": "false",
      "licensedContent": true,
      "contentRating": {},
      "projection": "rectangular"
    },
    "liveStreamingDetails": {
      "actualStartTime": "2023-05-05T01:59:24Z",
      "actualEndTime": "2023-05-05T03:42:42Z",
      "scheduledStartTime": "2023-05-05T02:00:00Z"
    }
  },
  "YeJWadIzS3c": {
    "id": "YeJWadIzS3c",
    "snippet": {
      "publishedAt": "2023-05-03T04:21:31Z",
      "channelId": "UCbwtBGLYpea4eIk-gocqJuw",
      "title": "\u3010Banjo-Kazooie\u3011THE ADVENTURE BEGINS!\u3010PRISMProject | Lana Shikami\u3011",
      "channelTitle": "Lana Shikami / \u7345\u5b88\u30e9\u30ca [PRISM Project]"
    },
    "contentDetails": {
      "duration": "PT2H9M34S",
      "dimension": "2d",
      "definition": "hd",
      "caption": "false",
      "licensedContent": true,
      "contentRating": {},
      "projection": "rectangular"
    },
    "liveStreamingDetails": {
      "actualStartTime": "2023-05-03T01:57:12Z",
      "actualEndTime": "2023-05-03T04:06:49Z",
      "scheduledStartTime": "2023-05-03T02:00:00Z"
    }
  },
  "uJiQAF1IO0c": {
    "id": "uJiQAF1IO0c",
    "snippet": {
      "publishedAt": "2023-05-01T04:15:20Z",
      "channelId": "UCbwtBGLYpea4eIk-gocqJuw",
      "title": "\u3010DINKUM\u3011NO THOUGHTS ONLY MINE\u3010PRISMProject | Lana Shikami\u3011",
      "channelTitle": "Lana Shikami / \u7345\u5b88\u30e9\u30ca [PRISM Project]"
    },
    "contentDetails": {
      "duration": "PT2H3M14S",
      "dimension": "2d",
      "definition": "hd",
      "caption": "false",
      "licensedContent": true,
      "contentRating": {},
      "projection": "rectangular"
    },
    "liveStreamingDetails": {
      "actualStartTime": "2023-05-01T01:58:15Z",
      "actualEndTime": "2023-05-01T04:01:29Z",
      "scheduledStartTime": "2023-05-01T02:00:00Z"
    }
  },
  "SPj5mQKqQmc": {
    "id": "SPj5mQKqQmc",
    "snippet": {
      "publishedAt": "2023-04-29T23:39:18Z",
      "channelId": "UCbwtBGLYpea4eIk-gocqJuw",
      "title": "\u3010DEBUT 2.0\u3011BACK SO SOON? \ud83d\ude09\u3010PRISMProject | Lana Shikami\u3011",
      "channelTitle": "Lana Shikami / \u7345\u5b88\u30e9\u30ca [PRISM Project]"
    },
    "contentDetails": {
      "duration": "PT1H34M58S",
      "dimension": "2d",
      "definition": "hd",
      "caption": "false",
      "licensedContent": true,
      "contentRating": {},
      "projection": "rectangular"
    },
    "liveStreamingDetails": {
      "actualStartTime": "2023-04-29T21:57:50Z",
      "actualEndTime": "2023-04-29T23:32:44Z",
      "scheduledStartTime": "2023-04-29T22:00:00Z"
    }
  },
  "cbKCmUEdqbw": {
    "id": "cbKCmUEdqbw",
    "snippet": {
      "publishedAt": "2023-04-29T05:07:54Z",
      "channelId": "UCbwtBGLYpea4eIk-gocqJuw",
      "title": "\u3010DEBUT STREAM\u3011It's time to praise the sun!\u3010PRISM Project Gen 5\u3011",
      "channelTitle": "Lana Shikami / \u7345\u5b88\u30e9\u30ca [PRISM Project]"
    },
    "contentDetails": {
      "duration": "PT1H47S",
      "dimension": "2d",
      "definition": "hd",
      "caption": "false",
      "licensedContent": true,
      "contentRating": {},
      "projection": "rectangular"
    },
    "liveStreamingDetails": {
      "actualStartTime": "2023-04-29T04:01:04Z",
      "actualEndTime": "2023-04-29T05:01:58Z",
      "scheduledStartTime": "2023-04-29T04:00:00Z"
    }
  },
  "rn3d6WjZXJQ": {
    "id": "rn3d6WjZXJQ",
    "snippet": {
      "publishedAt": "2023-04-29T05:05:49Z",
      "channelId": "UCbwtBGLYpea4eIk-gocqJuw",
      "title": "Ladylike - KIRA\u3010Lana Shikami Cover\u3011",
      "channelTitle": "Lana Shikami / \u7345\u5b88\u30e9\u30ca [PRISM Project]"
    },
    "contentDetails": {
      "duration": "PT3M27S",
      "dimension": "2d",
      "definition": "hd",
      "caption": "false",
      "licensedContent": false,
      "contentRating": {},
      "projection": "rectangular"
    },
    "liveStreamingDetails": {
      "actualStartTime": "2023-04-29T05:05:49Z",
      "actualEndTime": "2023-04-29T05:10:09Z",
      "scheduledStartTime": "2023-04-29T05:05:21Z"
    }
  },
  "FwV8ApdJLhQ": {
    "id": "FwV8ApdJLhQ",
    "snippet": {
      "publishedAt": "2023-04-28T12:26:21Z",
      "channelId": "UCbwtBGLYpea4eIk-gocqJuw",
      "title": "Lana Shikami / \u7345\u5b88\u30e9\u30ca [PRISM Project] Live Stream",
      "channelTitle": "Lana Shikami / \u7345\u5b88\u30e9\u30ca [PRISM Project]"
    },
    "liveStreamingDetails": {
      "activeLiveChatId": "Cg0KC0Z3VjhBcGRKTGhRKicKGFVDYnd0QkdMWXBlYTRlSWstZ29jcUp1dxILRndWOEFwZEpMaFE"
    }
  },
  "60RJ_il5F6A": {
    "id": "60RJ_il5F6A",
    "snippet": {
      "publishedAt": "2023-04-27T19:48:55Z",
      "channelId": "UCbwtBGLYpea4eIk-gocqJuw",
      "title": "PRISM PROJECT GEN 5 DEBUT TOMORROW!!",
      "channelTitle": "Lana Shikami / \u7345\u5b88\u30e9\u30ca [PRISM Project]"
    },
    "contentDetails": {
      "duration": "PT21S",
      "dimension": "2d",
      "definition": "hd",
      "caption": "false",
      "licensedContent": true,
      "contentRating": {},
      "projection": "rectangular"
    }
  },
  "J369I2473jI": {
    "id": "J369I2473jI",
    "snippet": {
      "publishedAt": "2023-04-27T17:00:19Z",
      "channelId": "UCbwtBGLYpea4eIk-gocqJuw",
      "title": "Can you resist this vtubers Dommy Mommy voice?",
      "channelTitle": "Lana Shikami / \u7345\u5b88\u30e9\u30ca [PRISM Project]"
    },
    "contentDetails": {
      "duration": "PT16S",
      "dimension": "2d",
      "definition": "hd",
      "caption": "false",
      "licensedContent": true,
      "contentRating": {},
      "projection": "rectangular"
    }
  },
  "3XU1wCh1gZs": {
    "id": "3XU1wCh1gZs",
    "snippet": {
      "publishedAt": "2023-04-26T22:09:53Z",
      "channelId": "UCbwtBGLYpea4eIk-gocqJuw",
      "title": "This VTuber is a FAKE KIWI?! \ud83e\udd14",
      "channelTitle": "Lana Shikami / \u7345\u5b88\u30e9\u30ca [PRISM Project]"
    },
    "contentDetails": {
      "duration": "PT34S",
      "dimension": "2d",
      "definition": "hd",
      "caption": "false",
      "licensedContent": true,
      "contentRating": {},
      "projection": "rectangular"
    }
  },
  "rhP9XMDZmEM": {
    "id": "rhP9XMDZmEM",
    "snippet": {
      "publishedAt": "2023-04-25T21:00:30Z",
      "channelId": "UCbwtBGLYpea4eIk-gocqJuw",
      "title": "Is my voice CAPTIVATING? \ud83e\udd14",
      "channelTitle": "Lana Shikami / \u7345\u5b88\u30e9\u30ca [PRISM Project]"
    },
    "contentDetails": {
      "duration": "PT10S",
      "dimension": "2d",
      "definition": "hd",
      "caption": "false",
      "licensedContent": true,
      "contentRating": {},
      "projection": "rectangular"
    }
  },
  "nDXKpzuzYQk": {
    "id": "nDXKpzuzYQk",
    "snippet": {
      "publishedAt": "2023-04-24T22:32:59Z",
      "channelId": "UCbwtBGLYpea4eIk-gocqJuw",
      "title": "What is THAT?!",
      "channelTitle": "Lana Shikami / \u7345\u5b88\u30e9\u30ca [PRISM Project]"
    },
    "contentDetails": {
      "duration": "PT14S",
      "dimension": "2d",
      "definition": "hd",
      "caption": "false",
      "licensedContent": true,
      "contentRating": {},
      "projection": "rectangular"
    }
  },
  "YsIq3rnkr90": {
    "id": "YsIq3rnkr90",
    "snippet": {
      "publishedAt": "2023-04-24T02:22:55Z",
      "channelId": "UCbwtBGLYpea4eIk-gocqJuw",
      "title": "Making ASMR and having ADHD is FUN!",
      "channelTitle": "Lana Shikami / \u7345\u5b88\u30e9\u30ca [PRISM Project]"
    },
    "contentDetails": {
      "duration": "PT23S",
      "dimension": "2d",
      "definition": "hd",
      "caption": "false",
      "licensedContent": true,
      "contentRating": {},
      "projection": "rectangular"
    }
  },
  "Op42EZ26vs4": {
    "id": "Op42EZ26vs4",
    "snippet": {
      "publishedAt": "2023-04-22T22:24:47Z",
      "channelId": "UCbwtBGLYpea4eIk-gocqJuw",
      "title": "Did you just call me mommy?",
      "channelTitle": "Lana Shikami / \u7345\u5b88\u30e9\u30ca [PRISM Project]"
    },
    "contentDetails": {
      "duration": "PT18S",
      "dimension": "2d",
      "definition": "hd",
      "caption": "false",
      "licensedContent": true,
      "contentRating": {},
      "projection": "rectangular"
    }
  },
  "1GyrSUK8Za8": {
    "id": "1GyrSUK8Za8",
    "snippet": {
      "publishedAt": "2023-04-22T00:00:00Z",
      "channelId": "UCbwtBGLYpea4eIk-gocqJuw",
      "title": "Hi",
      "channelTitle": "Lana Shikami / \u7345\u5b88\u30e9\u30ca [PRISM Project]"
    },
    "contentDetails": {
      "duration": "PT15S",
      "dimension": "2d",
      "definition": "hd",
      "caption": "false",
      "licensedContent": true,
      "contentRating": {},
      "projection": "rectangular"
    }
  }
}